aws_cdk/aws_codepipeline_actions/__init__.py
aws_cdk/aws_codepipeline_actions/py.typed
aws_cdk/aws_codepipeline_actions/_jsii/__init__.py
aws_cdk/aws_codepipeline_actions/_jsii/aws-codepipeline-actions@1.204.0.jsii.tgz
aws_cdk.aws_codepipeline_actions-1.204.0.dist-info/LICENSE
aws_cdk.aws_codepipeline_actions-1.204.0.dist-info/METADATA
aws_cdk.aws_codepipeline_actions-1.204.0.dist-info/NOTICE
aws_cdk.aws_codepipeline_actions-1.204.0.dist-info/WHEEL
aws_cdk.aws_codepipeline_actions-1.204.0.dist-info/top_level.txt
aws_cdk.aws_codepipeline_actions-1.204.0.dist-info/RECORD
