Metadata-Version: 2.1
Name: aws-cdk.aws-codepipeline-actions
Version: 1.204.0
Summary: Concrete Actions for AWS Code Pipeline
Home-page: https://github.com/aws/aws-cdk
Author: Amazon Web Services
License: Apache-2.0
Project-URL: Source, https://github.com/aws/aws-cdk.git
Classifier: Intended Audience :: Developers
Classifier: Operating System :: OS Independent
Classifier: Programming Language :: JavaScript
Classifier: Programming Language :: Python :: 3 :: Only
Classifier: Programming Language :: Python :: 3.7
Classifier: Programming Language :: Python :: 3.8
Classifier: Programming Language :: Python :: 3.9
Classifier: Programming Language :: Python :: 3.10
Classifier: Programming Language :: Python :: 3.11
Classifier: Typing :: Typed
Classifier: Development Status :: 7 - Inactive
Classifier: License :: OSI Approved
Classifier: Framework :: AWS CDK
Classifier: Framework :: AWS CDK :: 1
Requires-Python: ~=3.7
License-File: LICENSE
License-File: NOTICE
Requires-Dist: aws-cdk.aws-cloudformation (==1.204.0)
Requires-Dist: aws-cdk.aws-codebuild (==1.204.0)
Requires-Dist: aws-cdk.aws-codecommit (==1.204.0)
Requires-Dist: aws-cdk.aws-codedeploy (==1.204.0)
Requires-Dist: aws-cdk.aws-codepipeline (==1.204.0)
Requires-Dist: aws-cdk.aws-ec2 (==1.204.0)
Requires-Dist: aws-cdk.aws-ecr (==1.204.0)
Requires-Dist: aws-cdk.aws-ecs (==1.204.0)
Requires-Dist: aws-cdk.aws-events-targets (==1.204.0)
Requires-Dist: aws-cdk.aws-events (==1.204.0)
Requires-Dist: aws-cdk.aws-iam (==1.204.0)
Requires-Dist: aws-cdk.aws-kms (==1.204.0)
Requires-Dist: aws-cdk.aws-lambda (==1.204.0)
Requires-Dist: aws-cdk.aws-s3 (==1.204.0)
Requires-Dist: aws-cdk.aws-sns-subscriptions (==1.204.0)
Requires-Dist: aws-cdk.aws-sns (==1.204.0)
Requires-Dist: aws-cdk.aws-stepfunctions (==1.204.0)
Requires-Dist: aws-cdk.core (==1.204.0)
Requires-Dist: constructs (<4.0.0,>=3.3.69)
Requires-Dist: jsii (<2.0.0,>=1.84.0)
Requires-Dist: publication (>=0.0.3)
Requires-Dist: typeguard (~=2.13.3)
